README.rst
setup.py
enhydris/__init__.py
enhydris/urls.py
enhydris/wsgi.py
enhydris.egg-info/PKG-INFO
enhydris.egg-info/SOURCES.txt
enhydris.egg-info/dependency_links.txt
enhydris.egg-info/requires.txt
enhydris.egg-info/top_level.txt
enhydris/api/__init__.py
enhydris/api/models.py
enhydris/api/permissions.py
enhydris/api/serializers.py
enhydris/api/tests.py
enhydris/api/urls.py
enhydris/api/views.py
enhydris/bin/enhydris-admin
enhydris/conf/manage.py
enhydris/conf/settings.py
enhydris/hcore/__init__.py
enhydris/hcore/admin.py
enhydris/hcore/context_processors.py
enhydris/hcore/decorators.py
enhydris/hcore/forms.py
enhydris/hcore/models.py
enhydris/hcore/templates
enhydris/hcore/urls.py
enhydris/hcore/utils.py
enhydris/hcore/views.py
enhydris/hcore/widgets.py
enhydris/hcore/migrations/0001_initial.py
enhydris/hcore/migrations/__init__.py
enhydris/hcore/static/css/enhydris.css
enhydris/hcore/static/css/olmap.css
enhydris/hcore/static/images/drop_marker.png
enhydris/hcore/static/images/drop_marker_cyan.png
enhydris/hcore/static/images/drop_marker_green.png
enhydris/hcore/static/images/drop_marker_orange.png
enhydris/hcore/static/images/drop_marker_selected.png
enhydris/hcore/static/images/help_files/image001.gif
enhydris/hcore/static/images/help_files/image002.gif
enhydris/hcore/static/images/help_files/image003.gif
enhydris/hcore/static/images/help_files/image004.gif
enhydris/hcore/static/images/help_files/image005.gif
enhydris/hcore/static/images/help_files/image006.gif
enhydris/hcore/static/images/help_files/image007.gif
enhydris/hcore/static/images/help_files/image008.gif
enhydris/hcore/static/images/help_files/image009.jpg
enhydris/hcore/static/images/help_files/image010.gif
enhydris/hcore/static/images/help_files/image011.gif
enhydris/hcore/static/images/help_files/image012.gif
enhydris/hcore/static/images/help_files/image013.gif
enhydris/hcore/static/images/help_files/image014.gif
enhydris/hcore/static/images/help_files/image015.gif
enhydris/hcore/static/images/help_files/image016.gif
enhydris/hcore/static/images/help_files/image017.jpg
enhydris/hcore/static/images/help_files/image018.jpg
