Metadata-Version: 1.0
Name: enhydris
Version: 0.8.0
Summary: Web application for meteorological data storage
Home-page: UNKNOWN
Author: Antonis Christofides
Author-email: anthony@itia.ntua.gr
License: AGPL3
Platform: UNKNOWN
